{
    "accounts": [
        {
            "username": "Hồ Thanh My",
            "password": "Nguyen2004nam@",
            "email": "",
            "linked_golike": "",
            "status": "",
            "original_tab": "G68T7XA6RKFQBQAI"
        },
        {
            "username": "Phạm Tường Tú",
            "password": "Nguyen2004nam@",
            "email": "",
            "linked_golike": "",
            "status": "",
            "original_tab": "KBYPBE7SAQEYUK6P"
        },
        {
            "username": "Hồ Thị Cường",
            "password": "Nguyen2004nam@",
            "email": "",
            "linked_golike": "",
            "status": "",
            "original_tab": "R58M82TQCYM"
        },
        {
            "username": "Đặng Quốc Quỳnh",
            "password": "Nguyen2004nam@",
            "email": "",
            "linked_golike": "",
            "status": "",
            "original_tab": "SX1LHMB212000071"
        },
        {
            "username": "Trần Hạnh",
            "password": "Nguyen2004nam@",
            "email": "",
            "linked_golike": "",
            "status": "",
            "original_tab": "ce0717179af5270b027e"
        },
        {
            "username": "dim.phng39112",
            "password": "Nguyen2004nam@",
            "email": "",
            "linked_golike": "",
            "status": "",
            "original_tab": "832d837"
        },
        {
            "username": "Tô Bảo Quỳnh",
            "password": "Nguyen2004nam@",
            "email": "",
            "linked_golike": "",
            "status": "",
            "original_tab": "9887a8314d53414359"
        },
        {
            "username": "Hồ Nhật Tú",
            "password": "Nguyen2004nam@",
            "email": "",
            "linked_golike": "",
            "status": "",
            "original_tab": "9887e0324635313539"
        },
        {
            "username": "Lê Quốc Quỳnh",
            "password": "Nguyen2004nam@",
            "email": "",
            "linked_golike": "",
            "status": "",
            "original_tab": "9887fc3748494e4d47"
        },
        {
            "username": "Tô Thanh My",
            "password": "Nguyen2004nam@",
            "email": "",
            "linked_golike": "",
            "status": "",
            "original_tab": "9888d33545344c4834"
        },
        {
            "username": "Đỗ Ngọc Dũng",
            "password": "Nguyen2004nam@",
            "email": "",
            "linked_golike": "",
            "status": "",
            "original_tab": "9888d33545344c4834"
        },
        {
            "username": "a",
            "password": "",
            "email": "",
            "linked_golike": "",
            "status": "",
            "original_tab": ""
        },
        {
            "username": "Bùi Gia Thy",
            "password": "Nguyen2004nam@",
            "email": "",
            "linked_golike": "",
            "status": "",
            "original_tab": "9888d33545344c4834"
        },
        {
            "username": "Hồ Hạnh",
            "password": "Nguyen2004nam@",
            "email": "",
            "linked_golike": "",
            "status": "",
            "original_tab": "9888d33545344c4834"
        },
        {
            "username": "Nguyễn Thành Thy",
            "password": "Nguyen2004nam@",
            "email": "",
            "linked_golike": "",
            "status": "",
            "original_tab": "9888d33545344c4834"
        }
    ]
}